bucketbase/__init__.py
bucketbase/_queue_binary_io.py
bucketbase/backup_multi_bucket.py
bucketbase/cached_immutable_bucket.py
bucketbase/errors.py
bucketbase/file_lock.py
bucketbase/fs_bucket.py
bucketbase/ibucket.py
bucketbase/memory_bucket.py
bucketbase/minio_bucket.py
bucketbase/named_lock_manager.py
bucketbase/utils.py
bucketbase-1.5.4.dist-info/METADATA
bucketbase-1.5.4.dist-info/WHEEL
bucketbase-1.5.4.dist-info/RECORD
