Metadata-Version: 2.4
Name: bucketbase
Version: 1.5.4
Summary: bucketbase
License: MIT
Author: Andrei Suiu
Author-email: andrei.suiu@gmail.com
Requires-Python: >=3.10,<4.0.0
Classifier: License :: OSI Approved :: MIT License
Classifier: Programming Language :: Python :: 3
Classifier: Programming Language :: Python :: 3.10
Classifier: Programming Language :: Python :: 3.11
Classifier: Programming Language :: Python :: 3.12
Classifier: Programming Language :: Python :: 3.13
Classifier: Programming Language :: Python :: 3.14
Provides-Extra: minio
Requires-Dist: StrEnum (>=0.4.0)
Requires-Dist: exceptiongroup (>=1.0.0) ; python_version < "3.11"
Requires-Dist: filelock (>=3.20.0)
Requires-Dist: minio (>=7.2.4,<=8.0.0) ; extra == "minio"
Requires-Dist: multiminio (>=1.0.2) ; extra == "minio"
Requires-Dist: pyxtension (>=1.17.1)
Requires-Dist: requests (>=2.25.1)
Requires-Dist: streamerate (>=1.2.1)
Project-URL: Repository, https://github.com/asuiu/bucketbase
